[
  {
    "nome": "Franco Albini",
    "nato": 1905,
    "morto": 1977,
    "bio": "Architetto e designer razionalista milanese.",
    "foto": "franco albini.jpg",
    "y": null
  },
  {
    "nome": "Vico Magistretti",
    "nato": 1920,
    "morto": 2006,
    "bio": "Designer e architetto milanese.",
    "foto": "vico magistretti.jpg",
    "y": null
  },
  {
    "nome": "Achille Castiglioni",
    "nato": 1918,
    "morto": 2002,
    "bio": "Maestro del design funzionale e ironico.",
    "foto": "achille castiglioni.jpg",
    "y": null
  },
  {
    "nome": "Renzo Piano",
    "nato": 1937,
    "morto": null,
    "bio": "Architetto, ha lavorato nello studio di Albini.",
    "foto": "renzo piano.jpg",
    "y": null
  },
  {
    "nome": "Nathan Rogers",
    "nato": 1912,
    "morto": 1969,
    "bio": "Critico e designer, fondatore di Casabella.",
    "foto": "rogers.jpg",
    "y": null
  }
]